odoo/addons/account_balance_zero/README.rst
odoo/addons/account_balance_zero/__init__.py
odoo/addons/account_balance_zero/__manifest__.py
odoo/addons/account_balance_zero/static/description/icon.png
odoo/addons/account_balance_zero/wizard/__init__.py
odoo/addons/account_balance_zero/wizard/account_balance_zero.py
odoo/addons/account_balance_zero/wizard/account_balance_zero.xml
odoo13_addon_account_balance_zero-13.0.1.0.0.dist-info/METADATA
odoo13_addon_account_balance_zero-13.0.1.0.0.dist-info/WHEEL
odoo13_addon_account_balance_zero-13.0.1.0.0.dist-info/top_level.txt
odoo13_addon_account_balance_zero-13.0.1.0.0.dist-info/RECORD
